pyrodigal/_translation.h
pyrodigal/lib.pyi
pyrodigal/CMakeLists.txt
pyrodigal/_connection.h
pyrodigal/lib.pxd
pyrodigal/__init__.py
pyrodigal/cli.py
pyrodigal/lib.pyx
pyrodigal/_sequence.h
pyrodigal/py.typed
pyrodigal/_sequence.pxd
pyrodigal/_connection.pxd
pyrodigal/lib.cpython-310-darwin.so
pyrodigal/__main__.py
pyrodigal/impl/generic.h
pyrodigal/impl/swar64.h
pyrodigal/impl/sse2.pyx
pyrodigal/impl/neon.h
pyrodigal/impl/avx2.h
pyrodigal/impl/neon.cpython-310-darwin.so
pyrodigal/impl/CMakeLists.txt
pyrodigal/impl/swar64.pxd
pyrodigal/impl/neon.pxd
pyrodigal/impl/mmx.h
pyrodigal/impl/avx512.pyx
pyrodigal/impl/avx2.pxd
pyrodigal/impl/__init__.pxd
pyrodigal/impl/mmx.pxd
pyrodigal/impl/avx512.h
pyrodigal/impl/sse2.h
pyrodigal/impl/generic.pxd
pyrodigal/impl/generic.pyx
pyrodigal/impl/mmx.c
pyrodigal/impl/avx2.pyx
pyrodigal/impl/avx512.pxd
pyrodigal/impl/neon.pyx
pyrodigal/impl/generic.cpython-310-darwin.so
pyrodigal/impl/swar64.pyx
pyrodigal/impl/template.h
pyrodigal/impl/sse2.pxd
pyrodigal/impl/swar64.cpython-310-darwin.so
pyrodigal/tests/test_sequence.py
pyrodigal/tests/test_training_info.py
pyrodigal/tests/requirements.txt
pyrodigal/tests/test_genes.py
pyrodigal/tests/test_mask.py
pyrodigal/tests/test_nodes.py
pyrodigal/tests/__init__.py
pyrodigal/tests/test_doctest.py
pyrodigal/tests/test_gene_finder.py
pyrodigal/tests/test_connection_scorer.py
pyrodigal/tests/fasta.py
pyrodigal/tests/test_gene.py
pyrodigal/tests/data/KK037166.single.fna.gz
pyrodigal/tests/data/SRR492066.meta.faa.gz
pyrodigal/tests/data/MIIJ01000039.meta.fna.gz
pyrodigal/tests/data/SRR492066.fna.gz
pyrodigal/tests/data/KK037166.fna.gz
pyrodigal/tests/data/KK037166.meta.fna.gz
pyrodigal/tests/data/MIIJ01000039.meta+mask.faa.gz
pyrodigal/tests/data/MIIJ01000039.single.faa.gz
pyrodigal/tests/data/SRR492066.meta.tsv
pyrodigal/tests/data/MIIJ01000039.faa.gz
pyrodigal/tests/data/SRR492066.training.bin.gz
pyrodigal/tests/data/__init__.py
pyrodigal-3.7.0.dist-info/RECORD
pyrodigal-3.7.0.dist-info/WHEEL
pyrodigal-3.7.0.dist-info/entry_points.txt
pyrodigal-3.7.0.dist-info/METADATA
pyrodigal-3.7.0.dist-info/licenses/COPYING
