Metadata-Version: 2.4
Name: pyrodigal
Version: 3.7.0
Summary: Cython bindings and Python interface to Prodigal, an ORF finder for genomes and metagenomes.
Keywords: bioinformatics,genome,orf,gene,prodigal
Author-Email: Martin Larralde <martin.larralde@embl.de>
License-Expression: GPL-3.0-or-later
License-File: COPYING
Classifier: Development Status :: 5 - Production/Stable
Classifier: Intended Audience :: Developers
Classifier: Intended Audience :: Science/Research
Classifier: Operating System :: OS Independent
Classifier: Programming Language :: C
Classifier: Programming Language :: Cython
Classifier: Programming Language :: Python :: 3.7
Classifier: Programming Language :: Python :: 3.8
Classifier: Programming Language :: Python :: 3.9
Classifier: Programming Language :: Python :: 3.10
Classifier: Programming Language :: Python :: 3.11
Classifier: Programming Language :: Python :: 3.12
Classifier: Programming Language :: Python :: 3.13
Classifier: Programming Language :: Python :: Implementation :: CPython
Classifier: Programming Language :: Python :: Implementation :: PyPy
Classifier: Topic :: Scientific/Engineering :: Bio-Informatics
Classifier: Topic :: Scientific/Engineering :: Medical Science Apps.
Classifier: Typing :: Typed
Project-URL: Documentation, https://pyrodigal.readthedocs.io/en/stable/
Project-URL: Bug Tracker, https://github.com/althonos/pyrodigal/issues
Project-URL: Changelog, https://github.com/althonos/pyrodigal/blob/master/CHANGELOG.md
Project-URL: Coverage, https://codecov.io/gh/althonos/pyrodigal/
Project-URL: Builds, https://github.com/althonos/pyrodigal/actions
Project-URL: Paper, https://doi.org/10.21105/joss.04296
Project-URL: PyPI, https://pypi.org/project/pyrodigal
Requires-Python: >=3.7
Requires-Dist: archspec~=0.2.0
Provides-Extra: test
Requires-Dist: importlib-resources; python_version < "3.9" and extra == "test"
Provides-Extra: isal
Requires-Dist: isal~=1.1; extra == "isal"
Provides-Extra: lz4
Requires-Dist: lz4~=4.0; extra == "lz4"
Provides-Extra: zst
Requires-Dist: zstandard~=0.22; extra == "zst"
